usgsquakemon.py
usgs_quakemon-1.0.5.dist-info/licenses/LICENSE
usgs_quakemon-1.0.5.dist-info/METADATA
usgs_quakemon-1.0.5.dist-info/WHEEL
usgs_quakemon-1.0.5.dist-info/entry_points.txt
usgs_quakemon-1.0.5.dist-info/top_level.txt
usgs_quakemon-1.0.5.dist-info/RECORD
