Metadata-Version: 2.4
Name: usgs-quakemon
Version: 1.0.5
Summary: Monitor USGS earthquake feeds with Python 3 from a CLI terminal.
Author-email: Ryan Steed <ryan.steed.usa@pm.me>, baraclese <1628879+baraclese@users.noreply.github.com>
Maintainer-email: Ryan Steed <ryan.steed.usa@pm.me>
License-Expression: GPL-3.0-only
Project-URL: Homepage, https://github.com/ryan-steed-usa/usgs-quakemon
Project-URL: Issues, https://github.com/ryan-steed-usa/usgs-quakemon/issues
Keywords: earthquake,monitor,usgs,feed,terminal,cli
Classifier: Development Status :: 5 - Production/Stable
Classifier: Intended Audience :: Education
Classifier: Intended Audience :: End Users/Desktop
Classifier: Intended Audience :: Other Audience
Classifier: Intended Audience :: Science/Research
Classifier: Environment :: Console
Classifier: Topic :: Scientific/Engineering
Classifier: Topic :: Terminals
Classifier: Topic :: Utilities
Classifier: Programming Language :: Python :: 3
Classifier: Programming Language :: Python :: 3.10
Classifier: Programming Language :: Python :: 3.11
Classifier: Programming Language :: Python :: 3.12
Classifier: Programming Language :: Python :: 3.13
Classifier: Programming Language :: Python :: 3.14
Classifier: Programming Language :: Python :: 3 :: Only
Requires-Python: >=3.10
License-File: LICENSE
Requires-Dist: requests
Requires-Dist: tabulate
Dynamic: license-file
